queue_messaging/__init__.py
queue_messaging/configuration.py
queue_messaging/exceptions.py
queue_messaging/messaging.py
queue_messaging/data/__init__.py
queue_messaging/data/encoding.py
queue_messaging/data/fields.py
queue_messaging/data/structures.py
queue_messaging/services/__init__.py
queue_messaging/services/pubsub.py
queue_messaging/test_utils/__init__.py
queue_messaging/test_utils/json.py
queue_messaging/utils/__init__.py
queue_messaging/utils/environment_context.py
tests/data/__init__.py
tests/data/test_encoding.py
tests/data/test_fields.py
tests/data/test_structures.py
tests/services/__init__.py
tests/services/test_pubsub.py
queue_messaging-0.3.5.dist-info/AUTHORS
queue_messaging-0.3.5.dist-info/LICENSE
queue_messaging-0.3.5.dist-info/METADATA
queue_messaging-0.3.5.dist-info/WHEEL
queue_messaging-0.3.5.dist-info/top_level.txt
queue_messaging-0.3.5.dist-info/RECORD
