Metadata-Version: 2.1
Name: queue-messaging
Version: 0.3.5
Summary: Python queue messaging library.
Home-page: https://github.com/socialwifi/queue-messaging
Author: Social WiFi
Author-email: it@socialwifi.com
License: BSD
Platform: UNKNOWN
Classifier: Development Status :: 5 - Production/Stable
Classifier: Environment :: Console
Classifier: Intended Audience :: Developers
Classifier: License :: OSI Approved :: BSD License
Classifier: Operating System :: OS Independent
Classifier: Programming Language :: Python
Classifier: Programming Language :: Python :: 3
Classifier: Programming Language :: Python :: 3.5
Classifier: Programming Language :: Python :: 3.6
Requires-Dist: cached-property
Requires-Dist: google-cloud-core
Requires-Dist: google-cloud-pubsub (>=0.35)
Requires-Dist: marshmallow
Requires-Dist: netaddr
Requires-Dist: tenacity
